Workbook

Sheet Inputs
A1: Home Affordability Tool
A3: User Inputs
A5: Current annual wage | B5: 90000 | D5: Notes
A6: Wage appreciation % | B6: 0.04 | D6: All outputs below update automatically.
A7: Current annual savings rate | B7: 12000
A8: Current down payment saved | B8: 45000 | D8: Year 0 = today.
A9: Current home sale price | B9: 350000 | D9: Projection extends 5 years.
A10: Closing cost % of sale price | B10: 0.06 | D10: Purchase price is inflation-adjusted.
A11: Home sale price appreciation % | B11: 0.03 | D11: Affordability is based on max payment.
A12: Home purchase price appreciation % | B12: 0.03
A13: Max monthly payment | B13: 2800
A14: Mortgage rate | B14: 0.065
A15: Loan term years | B15: 30
A16: Down payment % | B16: 0.2
A17: Property tax % | B17: 0.012
A18: Insurance yearly | B18: 1400
A19: HOA monthly | B19: 0
A20: PMI % of loan | B20: 0.0075
A21: Inflation / discount rate | B21: 0.03

Sheet Projection
A1: Year | B1: Infl Adj | C1: Wage | D1: Savings | E1: Down Pmt | F1: Sale Price | G1: Buy Price | H1: Max Loan | I1: Max Buy P
A2: 0 | B2: =(1+Inputs!B21)^0 | C2: =Inputs!B5*(1+Inputs!B6)^0 | D2: =Inputs!B8+Inputs!B7*0 | E2: =D2 | F2: =Inputs!B9*(1+Inputs!B11)^0 | G2: =Inputs!B9*(1+Inputs!B12)^0 | H2: =PMT(Inputs!B14/12,Inputs!B15*12,-Inputs!B13)*12*Inputs!B16 + 0 | I2: =((Inputs!B13 - (G2*Inputs!B17/12) - (Inputs!B18/12) - Inputs!B19) / ((Inputs!B14/12)/(1-(1+Inputs!B14/12)^(-Inputs!B15*12)))) / (1-Inputs!B16)
A3: 1 | B3: =(1+Inputs!B21)^1 | C3: =Inputs!B5*(1+Inputs!B6)^1 | D3: =Inputs!B8+Inputs!B7*1 | E3: =D3 | F3: =Inputs!B9*(1+Inputs!B11)^1 | G3: =Inputs!B9*(1+Inputs!B12)^1 | H3: =PMT(Inputs!B14/12,Inputs!B15*12,-Inputs!B13)*12*Inputs!B16 + 0 | I3: =((Inputs!B13 - (G3*Inputs!B17/12) - (Inputs!B18/12) - Inputs!B19) / ((Inputs!B14/12)/(1-(1+Inputs!B14/12)^(-Inputs!B15*12)))) / (1-Inputs!B16)
A4: 2 | B4: =(1+Inputs!B21)^2 | C4: =Inputs!B5*(1+Inputs!B6)^2 | D4: =Inputs!B8+Inputs!B7*2 | E4: =D4 | F4: =Inputs!B9*(1+Inputs!B11)^2 | G4: =Inputs!B9*(1+Inputs!B12)^2 | H4: =PMT(Inputs!B14/12,Inputs!B15*12,-Inputs!B13)*12*Inputs!B16 + 0 | I4: =((Inputs!B13 - (G4*Inputs!B17/12) - (Inputs!B18/12) - Inputs!B19) / ((Inputs!B14/12)/(1-(1+Inputs!B14/12)^(-Inputs!B15*12)))) / (1-Inputs!B16)
A5: 3 | B5: =(1+Inputs!B21)^3 | C5: =Inputs!B5*(1+Inputs!B6)^3 | D5: =Inputs!B8+Inputs!B7*3 | E5: =D5 | F5: =Inputs!B9*(1+Inputs!B11)^3 | G5: =Inputs!B9*(1+Inputs!B12)^3 | H5: =PMT(Inputs!B14/12,Inputs!B15*12,-Inputs!B13)*12*Inputs!B16 + 0 | I5: =((Inputs!B13 - (G5*Inputs!B17/12) - (Inputs!B18/12) - Inputs!B19) / ((Inputs!B14/12)/(1-(1+Inputs!B14/12)^(-Inputs!B15*12)))) / (1-Inputs!B16)
A6: 4 | B6: =(1+Inputs!B21)^4 | C6: =Inputs!B5*(1+Inputs!B6)^4 | D6: =Inputs!B8+Inputs!B7*4 | E6: =D6 | F6: =Inputs!B9*(1+Inputs!B11)^4 | G6: =Inputs!B9*(1+Inputs!B12)^4 | H6: =PMT(Inputs!B14/12,Inputs!B15*12,-Inputs!B13)*12*Inputs!B16 + 0 | I6: =((Inputs!B13 - (G6*Inputs!B17/12) - (Inputs!B18/12) - Inputs!B19) / ((Inputs!B14/12)/(1-(1+Inputs!B14/12)^(-Inputs!B15*12)))) / (1-Inputs!B16)
A7: 5 | B7: =(1+Inputs!B21)^5 | C7: =Inputs!B5*(1+Inputs!B6)^5 | D7: =Inputs!B8+Inputs!B7*5 | E7: =D7 | F7: =Inputs!B9*(1+Inputs!B11)^5 | G7: =Inputs!B9*(1+Inputs!B12)^5 | H7: =PMT(Inputs!B14/12,Inputs!B15*12,-Inputs!B13)*12*Inputs!B16 + 0 | I7: =((Inputs!B13 - (G7*Inputs!B17/12) - (Inputs!B18/12) - Inputs!B19) / ((Inputs!B14/12)/(1-(1+Inputs!B14/12)^(-Inputs!B15*12)))) / (1-Inputs!B16)

Sheet Summary
A1: Current Affordability
A3: Key Output
A5: Current max purchase price | B5: =Projection!I2
A6: Next 5-year purchase price range | B6: =MIN(Projection!I2:I7)&" to "&MAX(Projection!I2:I7)
A7: Best year shown | B7: =MATCH(MAX(Projection!I2:I7),Projection!I2:I7,0)-1
A8: Based on monthly payment | B8: =Inputs!B13
A9: Inflation-adjusted today value | B9: =Projection!I2
A10: Estimated affordability lift by year 5 | B10: =Projection!I7-Projection!I2
A13: Method | B13: Affordability uses max payment, tax, insurance, HOA, PMI, down payment, and appreciation assumptions.
